belvaio_request_id/__init__.py
belvaio_request_id/logger.py
belvaio_request_id/middleware.py
belvaio_request_id/utils.py
belvaio_request_id-0.1.2.data/data/LICENSE
belvaio_request_id-0.1.2.dist-info/LICENSE
belvaio_request_id-0.1.2.dist-info/METADATA
belvaio_request_id-0.1.2.dist-info/WHEEL
belvaio_request_id-0.1.2.dist-info/top_level.txt
belvaio_request_id-0.1.2.dist-info/RECORD
