Metadata-Version: 2.1
Name: belvaio-request-id
Version: 0.1.2
Summary: An aiohttp utils to track request journey between services.
Home-page: https://github.com/belvo-finance/belvaio-request-id
Author: Belvo Finance, S.L.
Author-email: hello@belvo.co
License: Apache Software License 2.0
Platform: UNKNOWN
Classifier: Development Status :: 3 - Alpha
Classifier: Environment :: Web Environment
Classifier: Intended Audience :: Developers
Classifier: License :: OSI Approved :: Apache Software License
Classifier: Operating System :: OS Independent
Classifier: Natural Language :: English
Classifier: Programming Language :: Python :: 3
Classifier: Programming Language :: Python :: 3.7
Classifier: Programming Language :: Python :: 3.8
Requires-Python: >=3.7
License-File: LICENSE
Requires-Dist: aiohttp (>=3.5)
Provides-Extra: sentry
Requires-Dist: sentry-sdk ; extra == 'sentry'
